{"stringsAndLibcalls":["free_thunk","_setjmp_thunk"],"numargs":1,"calleesideeffect":{},"calls":[["f(ARG1)","f()","f()","f(FUN_00124ea0@1199776)"],["f(ARG1)","f()","f()","f(FUN_00167270@1471088)"],["f(ARG1)","f(_setjmp_thunk@1058864)"],["f(ARG1)","f(free_thunk@1058560)"],["f(ARG1)","f(FUN_0013e0f0@1302768)"]],"arg1":{"offsets":["1536 store","1168 store","1520 store","1152 store","1312 store","1304 store","1160 load\/store","520 store"],"isArray":false},"loads":["f(ARG1): (ARG1 + 1536)","f(ARG1): (ARG1 + 1160)"],"calleeloads":{},"sideeffect":["f(ARG1): (ARG1 + 1520): f(ARG1)","f(ARG1): (ARG1 + 1304): f()","f(ARG1): (ARG1 + 1168): f()","f(ARG1): (ARG1 + 1152): f()","f(ARG1): (ARG1 + 1312): f()","f(ARG1): (ARG1 + 1536): f(ARG1)","f(ARG1): (ARG1 + 520): f()","f(ARG1): (ARG1 + 1160): f()"],"return":["ARG1"]}