{"stringsAndLibcalls":["__stack_chk_fail_thunk"],"numargs":1,"calleesideeffect":{},"calls":[["f(ARG1)","f(ARG1)","f()","f(FUN_0011c800@1165312)"],["f(ARG1)","f(ARG1)","f()","f(FUN_0011c800@1165312)"],["f(ARG1)","f(ARG1)","f()","f(FUN_0011c800@1165312)"],["f(ARG1)","f(ARG1)","f()","f(FUN_0011c800@1165312)"],["f(ARG1)","f(ARG1)","f()","f(FUN_0011c800@1165312)"],["f(ARG1)","f(ARG1)","f()","f(FUN_0011c800@1165312)"],["f(__stack_chk_fail_thunk@1058736)"],["f(ARG1)","f(ARG1)","f()","f(FUN_0011c800@1165312)"],["f(ARG1)","f(ARG1)","f()","f(FUN_0011c800@1165312)"]],"arg1":{"0":{"offsets":["0 load","20 load","40 store","24 load"],"isArray":false},"352":{"offsets":["20 load","24 load"],"isArray":true},"464":{"offsets":["56 load\/store"],"isArray":false},"344":{"offsets":["20 load","24 load"],"isArray":false},"offsets":["416 load","324 load","420 load","260 load","424 load","280 load","412 load"],"336":{"offsets":["20 load","24 load"],"isArray":false},"328":{"offsets":["20 load","24 load"],"isArray":false},"isArray":true,"40":{"0":{"offsets":["0 store","1 store"],"isArray":true},"offsets":["8 load","24 load"],"isArray":true}},"loads":["f(ARG1): (f(ARG1) + 8)","f(ARG1): (ARG1 + 420)","f(ARG1): ARG1","f(ARG1): ([(ARG1 + 40)] + 24)","f(ARG1): ([(ARG1 + 40)] + 24)","f(ARG1): [(ARG1 + 40)]","f(ARG1): ARG1","f(ARG1): (ARG1 + 336)","f(ARG1): ARG1","f(ARG1): (ARG1 + 324)","f(ARG1): (ARG1 + 420)","f(ARG1): ARG1","f(ARG1): [ARG1]","f(ARG1): (f(ARG1) + 24)","f(ARG1): (f(ARG1) + 8)","f(ARG1): (ARG1 + 324)","f(ARG1): [(ARG1 + 40)]","f(ARG1): (f(ARG1) + 24)","f(ARG1): ARG1","f(ARG1): ([(ARG1 + 328)] + 24)","f(ARG1): (ARG1 + 40)","f(ARG1): [ARG1]","f(ARG1): ARG1","f(ARG1): (ARG1 + 416)","f(ARG1): [(ARG1 + 40)]","f(ARG1): [ARG1]","f(ARG1): (ARG1 + 416)","f(ARG1): (ARG1 + 40)","f(ARG1): (ARG1 + 40)","f(ARG1): [ARG1]","f(ARG1): [ARG1]","f(ARG1): ([(ARG1 + 40)] + 8)","f(ARG1): (ARG1 + 420)","f(ARG1): (ARG1 + 336)","f(ARG1): [(ARG1 + 40)]","f(ARG1): ([(ARG1 + 40)] + 8)","f(ARG1): (ARG1 + (f() + 208))","f(ARG1): [(ARG1 + 40)]","f(ARG1): (ARG1 + 324)","f(ARG1): ([(ARG1 + 40)] + 8)","f(ARG1): (ARG1 + 40)","f(ARG1): ([(ARG1 + 352)] + 24)","f(ARG1): ([(ARG1 + 40)] + 8)","f(ARG1): [ARG1]","f(ARG1): (ARG1 + (f() + 192))","f(ARG1): ([(ARG1 + ((f() + 40) * 8))] + 20)","f(ARG1): ([(ARG1 + 40)] + 8)","f(ARG1): ([(ARG1 + 40)] + 24)","f(ARG1): ([(ARG1 + 336)] + 24)","f(ARG1): ([(ARG1 + 40)] + 8)","f(ARG1): ([(ARG1 + 40)] + 8)","f(ARG1): ([(ARG1 + 40)] + 24)","f(ARG1): (ARG1 + 344)","f(ARG1): ([(ARG1 + 40)] + 8)","f(ARG1): (ARG1 + 344)","f(ARG1): ARG1","f(ARG1): ([(ARG1 + 40)] + 24)","f(ARG1): (ARG1 + 412)","f(ARG1): ([(ARG1 + 344)] + 24)","f(ARG1): [ARG1]","f(ARG1): ARG1","f(ARG1): [ARG1]","f(ARG1): (ARG1 + 416)","f(ARG1): [(ARG1 + 40)]","f(ARG1): [(ARG1 + 40)]","f(ARG1): ([(ARG1 + 40)] + 24)","f(ARG1): (ARG1 + 40)","f(ARG1): (ARG1 + 40)","f(ARG1): ARG1","f(ARG1): [(ARG1 + 40)]","f(ARG1): (ARG1 + 40)","f(ARG1): (ARG1 + 40)","f(ARG1): ARG1","f(ARG1): [ARG1]","f(ARG1): (ARG1 + 352)","f(ARG1): (ARG1 + 40)","f(ARG1): [(ARG1 + 40)]","f(ARG1): [ARG1]","f(ARG1): (ARG1 + 324)","f(ARG1): [(ARG1 + 40)]","f(ARG1): (ARG1 + 416)","f(ARG1): ([(ARG1 + 40)] + 8)","f(ARG1): (ARG1 + ((f() + 40) * 8))","f(ARG1): ([(ARG1 + 40)] + 8)","f(ARG1): (ARG1 + 420)","f(ARG1): ([(ARG1 + 40)] + 8)","f(ARG1): (f(ARG1) + 24)","f(ARG1): ([(ARG1 + 40)] + 8)","f(ARG1): (ARG1 + 416)","f(ARG1): ([(ARG1 + 40)] + 8)","f(ARG1): ([(ARG1 + 40)] + 24)","f(ARG1): ([(ARG1 + 40)] + 24)","f(ARG1): (ARG1 + 328)","f(ARG1): (ARG1 + 324)","f(ARG1): [(ARG1 + ((f() + 40) * 8))]","f(ARG1): ([(ARG1 + 40)] + 8)","f(ARG1): ([(ARG1 + 328)] + 20)","f(ARG1): (ARG1 + 352)","f(ARG1): [(ARG1 + 40)]","f(ARG1): ([(ARG1 + 336)] + 20)","f(ARG1): (ARG1 + 412)","f(ARG1): (ARG1 + 420)","f(ARG1): ([(ARG1 + ((f() + 40) * 8))] + 24)","f(ARG1): (ARG1 + 40)","f(ARG1): ([(ARG1 + 344)] + 24)","f(ARG1): (ARG1 + 412)","f(ARG1): ([(ARG1 + 40)] + 8)","f(ARG1): (ARG1 + 424)","f(ARG1): ([(ARG1 + 328)] + 20)","f(ARG1): ([(ARG1 + 40)] + 24)","f(ARG1): [(ARG1 + 40)]","f(ARG1): ([(ARG1 + 328)] + 24)","f(ARG1): ([(ARG1 + 336)] + 24)","f(ARG1): ([(ARG1 + 40)] + 8)","f(ARG1): (ARG1 + 40)","f(ARG1): ARG1","f(ARG1): ARG1","f(ARG1): ARG1","f(ARG1): ([(ARG1 + 40)] + 8)","f(ARG1): (ARG1 + 40)","f(ARG1): ([(ARG1 + 40)] + 24)","f(ARG1): (ARG1 + 40)","f(ARG1): ([(ARG1 + 40)] + 8)","f(ARG1): [ARG1]","f(ARG1): ([(ARG1 + 328)] + 20)","f(ARG1): (ARG1 + 420)","f(ARG1): [ARG1]","f(ARG1): ARG1","f(ARG1): [(ARG1 + 40)]","f(ARG1): ([(ARG1 + 40)] + 8)","f(ARG1): (ARG1 + 280)","f(ARG1): ([(ARG1 + 40)] + 8)","f(ARG1): (ARG1 + 328)","f(ARG1): ([(ARG1 + 40)] + 24)","f(ARG1): [(ARG1 + 40)]","f(ARG1): (ARG1 + 260)","f(ARG1): (ARG1 + 336)","f(ARG1): ([(ARG1 + 328)] + 24)","f(ARG1): (ARG1 + 40)","f(ARG1): ([(ARG1 + 40)] + 8)","f(ARG1): [(ARG1 + 40)]","f(ARG1): ([(ARG1 + 40)] + 24)","f(ARG1): (ARG1 + 336)","f(ARG1): (ARG1 + 416)","f(ARG1): [ARG1]","f(ARG1): ([(ARG1 + 40)] + 8)","f(ARG1): ([(ARG1 + 336)] + 24)","f(ARG1): ([(ARG1 + 336)] + 20)","f(ARG1): ([(ARG1 + 40)] + 8)","f(ARG1): (ARG1 + 336)","f(ARG1): ([(ARG1 + 336)] + 20)","f(ARG1): ([(ARG1 + 40)] + 8)","f(ARG1): ARG1","f(ARG1): (ARG1 + 412)","f(ARG1): (ARG1 + 464)","f(ARG1): [ARG1]","f(ARG1): (f(ARG1) + 8)","f(ARG1): [ARG1]","f(ARG1): ([(ARG1 + 40)] + 8)","f(ARG1): [(ARG1 + 40)]","f(ARG1): ([(ARG1 + 40)] + 8)","f(ARG1): ARG1","f(ARG1): (ARG1 + 40)","f(ARG1): ([(ARG1 + 40)] + 24)","f(ARG1): (ARG1 + 324)","f(ARG1): (ARG1 + 344)","f(ARG1): (ARG1 + 280)","f(ARG1): [(ARG1 + 40)]","f(ARG1): ARG1","f(ARG1): [ARG1]","f(ARG1): (ARG1 + 344)","f(ARG1): ([(ARG1 + 40)] + 24)","f(ARG1): ([(ARG1 + 464)] + 56)","f(ARG1): (ARG1 + 40)","f(ARG1): (f(ARG1) + 8)","f(ARG1): ([(ARG1 + 352)] + 20)","f(ARG1): ([(ARG1 + 336)] + 24)","f(ARG1): ([(ARG1 + 344)] + 20)","f(ARG1): (f(ARG1) + 24)","f(ARG1): ARG1","f(ARG1): (ARG1 + 344)","f(ARG1): ([(ARG1 + 40)] + 24)","f(ARG1): ARG1","f(ARG1): ([(ARG1 + 344)] + 24)","f(ARG1): [ARG1]","f(ARG1): ([(ARG1 + 344)] + 24)","f(ARG1): ARG1","f(ARG1): ([(ARG1 + 40)] + 8)","f(ARG1): ([(ARG1 + 344)] + 20)","f(ARG1): ([(ARG1 + 40)] + 8)","f(ARG1): (ARG1 + 324)","f(ARG1): (ARG1 + 352)","f(ARG1): ([(ARG1 + 40)] + 24)","f(ARG1): ([(ARG1 + 352)] + 20)","f(ARG1): [ARG1]","f(ARG1): [ARG1]","f(ARG1): (f(ARG1) + 8)","f(ARG1): [(ARG1 + 40)]","f(ARG1): (ARG1 + 352)","f(ARG1): (ARG1 + 40)","f(ARG1): (f(ARG1) + 8)","f(ARG1): (ARG1 + 352)","f(ARG1): (f(ARG1) + 24)","f(ARG1): (ARG1 + 328)","f(ARG1): ([(ARG1 + 352)] + 24)","f(ARG1): (ARG1 + 40)","f(ARG1): [ARG1]","f(ARG1): (ARG1 + 412)","f(ARG1): (ARG1 + 40)","f(ARG1): [(ARG1 + 40)]","f(ARG1): [(ARG1 + 40)]","f(ARG1): ([(ARG1 + 352)] + 20)","f(ARG1): ([(ARG1 + 40)] + 8)","f(ARG1): ([(ARG1 + 40)] + 8)","f(ARG1): ARG1","f(ARG1): (ARG1 + (f() + 224))","f(ARG1): ([(ARG1 + 40)] + 24)","f(ARG1): (ARG1 + 40)","f(ARG1): (ARG1 + 40)","f(ARG1): [ARG1]","f(ARG1): (ARG1 + 420)","f(ARG1): ARG1","f(ARG1): (ARG1 + 416)","f(ARG1): [(ARG1 + 40)]","f(ARG1): [(ARG1 + 40)]","f(ARG1): (ARG1 + 40)","f(ARG1): ([(ARG1 + 40)] + 8)","f(ARG1): [ARG1]","f(ARG1): ([(ARG1 + 40)] + 8)","f(ARG1): (ARG1 + 324)","f(ARG1): (ARG1 + 412)","f(ARG1): (ARG1 + 40)","f(ARG1): ARG1","f(ARG1): [(ARG1 + 40)]","f(ARG1): (ARG1 + 280)","f(ARG1): (ARG1 + 420)","f(ARG1): ([(ARG1 + 40)] + 8)","f(ARG1): ([(ARG1 + 40)] + 8)","f(ARG1): [ARG1]","f(ARG1): ([(ARG1 + 40)] + 8)","f(ARG1): [(ARG1 + 40)]","f(ARG1): ([(ARG1 + 40)] + 24)","f(ARG1): (ARG1 + 40)","f(ARG1): ([(ARG1 + 40)] + 8)","f(ARG1): ([(ARG1 + 40)] + 8)","f(ARG1): ARG1","f(ARG1): ([(ARG1 + 40)] + 8)","f(ARG1): (ARG1 + 324)","f(ARG1): (ARG1 + 40)","f(ARG1): ([(ARG1 + 344)] + 20)","f(ARG1): [ARG1]","f(ARG1): (f(ARG1) + 8)","f(ARG1): (ARG1 + 412)","f(ARG1): ([(ARG1 + 40)] + 24)","f(ARG1): (f(ARG1) + 8)","f(ARG1): ([(ARG1 + 328)] + 24)","f(ARG1): [(ARG1 + 40)]","f(ARG1): ([(ARG1 + 40)] + 8)","f(ARG1): ([(ARG1 + 40)] + 8)","f(ARG1): ([(ARG1 + 40)] + 24)"],"calleeloads":{},"sideeffect":["f(ARG1): [(ARG1 + 40)]: f(ARG1)","f(ARG1): [[(ARG1 + 40)]]: f(ARG1)","f(ARG1): [[(ARG1 + 40)]]: f(ARG1)","f(ARG1): f(ARG1): f()","f(ARG1): [[(ARG1 + 40)]]: f(ARG1)","f(ARG1): ([(ARG1 + 40)] + 8): f(ARG1)","f(ARG1): [[(ARG1 + 40)]]: f(ARG1)","f(ARG1): f(ARG1): f(ARG1)","f(ARG1): f(ARG1): f()","f(ARG1): ([ARG1] + 40): f()","f(ARG1): ([ARG1] + 40): f()","f(ARG1): [[(ARG1 + 40)]]: f()","f(ARG1): [[(ARG1 + 40)]]: f(ARG1)","f(ARG1): [(ARG1 + 40)]: f(ARG1)","f(ARG1): [[(ARG1 + 40)]]: f(ARG1)","f(ARG1): (f(ARG1) + 8): f(ARG1)","f(ARG1): ([(ARG1 + 40)] + 8): f(ARG1)","f(ARG1): ([ARG1] + 40): f()","f(ARG1): ([ARG1] + 40): f()","f(ARG1): f(ARG1): f(ARG1)","f(ARG1): [(ARG1 + 40)]: f(ARG1)","f(ARG1): ([(ARG1 + 40)] + 8): f(ARG1)","f(ARG1): [[(ARG1 + 40)]]: f()","f(ARG1): ([(ARG1 + 40)] + 8): f(ARG1)","f(ARG1): [(ARG1 + 40)]: f(ARG1)","f(ARG1): ([(ARG1 + 40)] + 8): f(ARG1)","f(ARG1): ([ARG1] + 40): f()","f(ARG1): ([(ARG1 + 40)] + 8): f(ARG1)","f(ARG1): f(ARG1): f()","f(ARG1): f(ARG1): f()","f(ARG1): [[(ARG1 + 40)]]: f(ARG1)","f(ARG1): f(ARG1): f(ARG1)","f(ARG1): [[(ARG1 + 40)]]: f()","f(ARG1): ([ARG1] + 40): f()","f(ARG1): ([ARG1] + 40): f()","f(ARG1): f(ARG1): f(ARG1)","f(ARG1): f(ARG1): f()","f(ARG1): [(ARG1 + 40)]: f(ARG1)","f(ARG1): [[(ARG1 + 40)]]: f()","f(ARG1): f(ARG1): f(ARG1)","f(ARG1): f(ARG1): f()","f(ARG1): (f(ARG1) + 8): f(ARG1)","f(ARG1): ([(ARG1 + 40)] + 8): f(ARG1)","f(ARG1): [[(ARG1 + 40)]]: f()","f(ARG1): ([(ARG1 + 40)] + 8): f(ARG1)","f(ARG1): ([ARG1] + 40): f()","f(ARG1): f(ARG1): f(ARG1)","f(ARG1): [(ARG1 + 40)]: f(ARG1)","f(ARG1): f(ARG1): f(ARG1)","f(ARG1): ([(ARG1 + 40)] + 8): f(ARG1)","f(ARG1): [(ARG1 + 40)]: f(ARG1)","f(ARG1): f(ARG1): f(ARG1)","f(ARG1): ([ARG1] + 40): f()","f(ARG1): [[(ARG1 + 40)]]: f(ARG1)","f(ARG1): f(ARG1): f(ARG1)","f(ARG1): ([ARG1] + 40): f()","f(ARG1): f(ARG1): f(ARG1)","f(ARG1): [(ARG1 + 40)]: f(ARG1)","f(ARG1): [(ARG1 + 40)]: f(ARG1)","f(ARG1): ([ARG1] + 40): f()","f(ARG1): [(ARG1 + 40)]: f(ARG1)","f(ARG1): ([ARG1] + 40): f()","f(ARG1): f(ARG1): f()","f(ARG1): ([(ARG1 + 40)] + 8): f(ARG1)","f(ARG1): ([(ARG1 + 40)] + 8): f(ARG1)","f(ARG1): [[(ARG1 + 40)]]: f(ARG1)","f(ARG1): ([(ARG1 + 40)] + 8): f(ARG1)","f(ARG1): f(ARG1): f(ARG1)","f(ARG1): [[(ARG1 + 40)]]: f()","f(ARG1): (f(ARG1) + 8): f(ARG1)","f(ARG1): [(ARG1 + 40)]: f(ARG1)","f(ARG1): ([ARG1] + 40): f()","f(ARG1): [(ARG1 + 40)]: f(ARG1)","f(ARG1): f(ARG1): f(ARG1)","f(ARG1): ([ARG1] + 40): f()","f(ARG1): [(ARG1 + 40)]: f(ARG1)","f(ARG1): ([(ARG1 + 40)] + 8): f(ARG1)","f(ARG1): [(ARG1 + 40)]: f(ARG1)","f(ARG1): ([ARG1] + 40): f()","f(ARG1): [[(ARG1 + 40)]]: f(ARG1)","f(ARG1): ([(ARG1 + 40)] + 8): f(ARG1)","f(ARG1): [[(ARG1 + 40)]]: f(ARG1)","f(ARG1): [(ARG1 + 40)]: f(ARG1)","f(ARG1): ([ARG1] + 40): f()","f(ARG1): [[(ARG1 + 40)]]: f()","f(ARG1): ([(ARG1 + 40)] + 8): f(ARG1)","f(ARG1): ([ARG1] + 40): f()","f(ARG1): ([(ARG1 + 464)] + 56): f(ARG1)","f(ARG1): [(ARG1 + 40)]: f(ARG1)","f(ARG1): ([ARG1] + 40): f()","f(ARG1): [(ARG1 + 40)]: f(ARG1)","f(ARG1): [(ARG1 + 40)]: f(ARG1)","f(ARG1): ([(ARG1 + 40)] + 8): f(ARG1)","f(ARG1): f(ARG1): f()","f(ARG1): ([(ARG1 + 40)] + 8): f(ARG1)","f(ARG1): [(ARG1 + 40)]: f(ARG1)","f(ARG1): f(ARG1): f()","f(ARG1): ([(ARG1 + 40)] + 8): f(ARG1)","f(ARG1): f(ARG1): f()","f(ARG1): [[(ARG1 + 40)]]: f()","f(ARG1): [(ARG1 + 40)]: f(ARG1)","f(ARG1): ([(ARG1 + 40)] + 8): f(ARG1)","f(ARG1): f(ARG1): f(ARG1)","f(ARG1): ([ARG1] + 40): f()","f(ARG1): ([ARG1] + 40): f()","f(ARG1): ([(ARG1 + 40)] + 8): f(ARG1)","f(ARG1): [[(ARG1 + 40)]]: f(ARG1)","f(ARG1): f(ARG1): f()","f(ARG1): (f(ARG1) + 8): f(ARG1)","f(ARG1): ([ARG1] + 40): f()","f(ARG1): ([ARG1] + 40): f()","f(ARG1): f(ARG1): f(ARG1)","f(ARG1): f(ARG1): f()","f(ARG1): f(ARG1): f(ARG1)","f(ARG1): ([ARG1] + 40): f()","f(ARG1): ([ARG1] + 40): f()","f(ARG1): f(ARG1): f(ARG1)"],"return":[]}