{"stringsAndLibcalls":[],"numargs":5,"loads":["f(ARG1 , ARG2 , ARG3): (f(ARG1 , ARG2 , ARG3) + 1)","f(ARG1): (ARG1 + 136)","f(ARG2 , ARG3): (f(ARG2 , ARG3) + 1)","f(ARG2 , ARG3): (f(ARG2 , ARG3) + 23)","f(ARG2 , ARG3): (f(ARG2 , ARG3) + 24)","f(ARG2 , ARG3): (f(ARG2 , ARG3) + 21)","f(ARG1 , ARG2 , ARG3): f(ARG1 , ARG2 , ARG3)","f(ARG2 , ARG3): [([ARG2] + (f(ARG3) * 8))]","f(ARG2 , ARG3): (f(ARG2 , ARG3) + 22)","f(ARG2 , ARG3): (f(ARG2 , ARG3) + 19)","f(ARG2 , ARG3): (f(ARG2 , ARG3) + 20)","f(ARG2 , ARG3): f(ARG2 , ARG3)","f(ARG2 , ARG3): (f(ARG2 , ARG3) + 17)","f(ARG2 , ARG3): (f(ARG2 , ARG3) + 16)","f(ARG2 , ARG3): (f(ARG2 , ARG3) + 18)","f(ARG2 , ARG3): ([ARG2] + (f(ARG3) * 8))","f(ARG2 , ARG3): f(ARG2 , ARG3)","f(ARG4): f(ARG4)","f(ARG2 , ARG3): (f(ARG2 , ARG3) + 31)","f(ARG2 , ARG3): (f(ARG2 , ARG3) + 29)","f(ARG2 , ARG3): (f(ARG2 , ARG3) + 30)","f(ARG2 , ARG3): (f(ARG2 , ARG3) + 27)","f(ARG2 , ARG3): (f(ARG2 , ARG3) + 28)","f(ARG2 , ARG3): (f(ARG2 , ARG3) + 25)","f(ARG2 , ARG3): (f(ARG2 , ARG3) + 26)","f(ARG1 , ARG2 , ARG3): f(ARG1 , ARG2 , ARG3)","f(ARG2): ARG2"],"sideeffect":["f(ARG4): f(ARG4): f(ARG2 , ARG3)","f(ARG4): (f(ARG4) + 48): f(ARG2 , ARG3)","f(ARG4): f(ARG4): f(ARG2 , ARG3)","f(ARG1 , ARG4): f(ARG1 , ARG4): f(ARG1 , ARG2 , ARG3)","f(ARG4): (f(ARG4) + 16): f()","f(ARG4): (f(ARG4) + 32): f(ARG2 , ARG3)","f(ARG1 , ARG4): f(ARG1 , ARG4): f(ARG1 , ARG2 , ARG3)","f(ARG4): [f(ARG4)]: f(ARG2 , ARG3)"],"arg3":"uint","arg2":{"0":{"0":{"offsets":["0 load","1 load","16 load","17 load","18 load","19 load","20 load","21 load","22 load","23 load","24 load","25 load","26 load","27 load","28 load","29 load","30 load","31 load"],"isArray":true},"offsets":[],"isArray":true},"offsets":[],"isArray":false},"arg5":"int","calleesideeffect":{},"arg4":{"0":{"offsets":["0 store","2 store","18 store","50 store","34 store"],"isArray":true},"offsets":[],"isArray":true},"calls":[],"arg1":{"offsets":["136 load"],"isArray":false},"calleeloads":{},"return":[]}