{"arg3":"int","stringsAndLibcalls":["__stack_chk_fail_thunk"],"arg2":"int","numargs":4,"calleesideeffect":{},"arg4":"int","calls":[["f()","f(__stack_chk_fail_thunk@1058912)"]],"arg1":{"offsets":["64 load","156 load"],"624":{"offsets":["48 load"],"isArray":false},"isArray":false,"160":{"0":{"offsets":["0 load"],"isArray":true},"16":{"offsets":["0 load"],"isArray":true},"offsets":[],"8":{"offsets":["0 load"],"isArray":true},"isArray":false}},"loads":["f(ARG1): ([([(ARG1 + 160)] + 16)] + f())","f(ARG1): [(ARG1 + 160)]","f(ARG1): ([(ARG1 + 160)] + 8)","f(ARG1): (([(ARG1 + 64)] * 4) + 1618944)","f(ARG1): (([(([(ARG1 + 64)] * 4) + 1618944)] * 4) + 1618720)","f(ARG1): [(ARG1 + 160)]","f(ARG1): ([(ARG1 + 624)] + 48)","f(ARG1): (([(ARG1 + 64)] * 4) + 1618944)","f(ARG1): (([(ARG1 + 64)] * 4) + 1618848)","f(ARG1): (([(([(ARG1 + 64)] * 4) + 1618752)] * 4) + 1618720)","f(ARG1): ([(ARG1 + 160)] + 16)","f(ARG1): (([(([(ARG1 + 64)] * 4) + 1618944)] * 4) + 1618720)","f(ARG1): ([([(ARG1 + 160)] + 8)] + f())","f(ARG1): (([(ARG1 + 64)] * 4) + 1618752)","f(ARG1): ([(ARG1 + 160)] + 8)","f(ARG1): (ARG1 + 64)","f(ARG1): (([(([(ARG1 + 64)] * 4) + 1618848)] * 4) + 1618720)","f(ARG1): (([(ARG1 + 64)] * 4) + 1618752)","f(ARG1): (([(ARG1 + 64)] * 4) + 1618848)","f(ARG1): (([(ARG1 + 64)] * 4) + 1618848)","f(ARG1): (([(([(ARG1 + 64)] * 4) + 1618944)] * 4) + 1618720)","f(ARG1): (([(([(ARG1 + 64)] * 4) + 1618848)] * 4) + 1618720)","f(ARG1): (ARG1 + 624)","f(ARG1): ([([(ARG1 + 160)] + 8)] + f())","f(ARG1): (ARG1 + 156)","f(ARG1): (([(([(ARG1 + 64)] * 4) + 1618848)] * 4) + 1618720)","f(ARG1): (([(([(ARG1 + 64)] * 4) + 1618752)] * 4) + 1618720)","f(ARG1): ([[(ARG1 + 160)]] + f())","f(ARG1): (([(([(ARG1 + 64)] * 4) + 1618944)] * 4) + 1618720)","f(ARG1): (([(ARG1 + 64)] * 4) + 1618944)","f(ARG1): (ARG1 + 160)","f(ARG1): (ARG1 + 160)","f(ARG1 , ARG2): f(ARG1 , ARG2)","f(ARG1): (([(ARG1 + 64)] * 4) + 1618848)","f(ARG1): (([(([(ARG1 + 64)] * 4) + 1618848)] * 4) + 1618720)","f(ARG1): ([([(ARG1 + 160)] + 16)] + f())","f(ARG1): (([(ARG1 + 64)] * 4) + 1618944)","f(ARG1): ([(ARG1 + 160)] + 16)"],"calleeloads":{},"sideeffect":["f(ARG1 , ARG2 , ARG3 , ARG4): ((([f(ARG1 , ARG2)] + (((((ARG3 \/ 8) * 8) + 1) * 64) + 64)) + ((ARG4 \/ 4) * 8)) + 2): f(RSP)","f(ARG1 , ARG2 , ARG3 , ARG4): ((([f(ARG1 , ARG2)] + (((((ARG3 \/ 8) * 8) + 1) * 64) + 384)) + ((ARG4 \/ 4) * 8)) + 4): f(RSP)","f(ARG1 , ARG2 , ARG3 , ARG4): ((([f(ARG1 , ARG2)] + (((((ARG3 \/ 8) * 8) + 1) * 64) + 128)) + ((ARG4 \/ 4) * 8)) + 2): f(RSP)","f(ARG1 , ARG2 , ARG3 , ARG4): ((([f(ARG1 , ARG2)] + ((((ARG3 \/ 8) * 8) + 1) * 64)) + ((ARG4 \/ 4) * 8)) + 4): f(RSP)","f(ARG1 , ARG2 , ARG3 , ARG4): ((([f(ARG1 , ARG2)] + ((ARG3 \/ 8) * 512)) + ((ARG4 \/ 4) * 8)) + 4): f(RSP)","f(ARG1 , ARG2 , ARG3 , ARG4): ((([f(ARG1 , ARG2)] + (((((ARG3 \/ 8) * 8) + 1) * 64) + 128)) + ((ARG4 \/ 4) * 8)) + 6): f(RSP)","f(ARG1 , ARG2 , ARG3 , ARG4): ((([f(ARG1 , ARG2)] + (((((ARG3 \/ 8) * 8) + 1) * 64) + 64)) + ((ARG4 \/ 4) * 8)) + 6): f(RSP)","f(ARG1 , ARG2 , ARG3 , ARG4): (([f(ARG1 , ARG2)] + ((((ARG3 \/ 8) * 8) + 1) * 64)) + ((ARG4 \/ 4) * 8)): f(RSP)","f(ARG1 , ARG2 , ARG3 , ARG4): (([f(ARG1 , ARG2)] + (((((ARG3 \/ 8) * 8) + 1) * 64) + 256)) + ((ARG4 \/ 4) * 8)): f(RSP)","f(ARG1 , ARG2 , ARG3 , ARG4): ((([f(ARG1 , ARG2)] + (((((ARG3 \/ 8) * 8) + 1) * 64) + 384)) + ((ARG4 \/ 4) * 8)) + 6): f(RSP)","f(ARG1 , ARG2 , ARG3 , ARG4): ((([f(ARG1 , ARG2)] + (((((ARG3 \/ 8) * 8) + 1) * 64) + 128)) + ((ARG4 \/ 4) * 8)) + 4): f(RSP)","f(ARG1 , ARG2 , ARG3 , ARG4): ((([f(ARG1 , ARG2)] + ((ARG3 \/ 8) * 512)) + ((ARG4 \/ 4) * 8)) + 2): f(RSP)","f(ARG1 , ARG2 , ARG3 , ARG4): ((([f(ARG1 , ARG2)] + (((((ARG3 \/ 8) * 8) + 1) * 64) + 320)) + ((ARG4 \/ 4) * 8)) + 4): f(RSP)","f(ARG1 , ARG2 , ARG3 , ARG4): ((([f(ARG1 , ARG2)] + (((((ARG3 \/ 8) * 8) + 1) * 64) + 384)) + ((ARG4 \/ 4) * 8)) + 2): f(RSP)","f(ARG1 , ARG2 , ARG3 , ARG4): (([f(ARG1 , ARG2)] + ((ARG3 \/ 8) * 512)) + ((ARG4 \/ 4) * 8)): f(RSP)","f(ARG1 , ARG2 , ARG3 , ARG4): ((([f(ARG1 , ARG2)] + (((((ARG3 \/ 8) * 8) + 1) * 64) + 192)) + ((ARG4 \/ 4) * 8)) + 2): f(RSP)","f(ARG1 , ARG2 , ARG3 , ARG4): ((([f(ARG1 , ARG2)] + (((((ARG3 \/ 8) * 8) + 1) * 64) + 192)) + ((ARG4 \/ 4) * 8)) + 4): f(RSP)","f(ARG1 , ARG2 , ARG3 , ARG4): (([f(ARG1 , ARG2)] + (((((ARG3 \/ 8) * 8) + 1) * 64) + 320)) + ((ARG4 \/ 4) * 8)): f(RSP)","f(ARG1 , ARG2 , ARG3 , ARG4): ((([f(ARG1 , ARG2)] + (((((ARG3 \/ 8) * 8) + 1) * 64) + 320)) + ((ARG4 \/ 4) * 8)) + 6): f(RSP)","f(ARG1 , ARG2 , ARG3 , ARG4): ((([f(ARG1 , ARG2)] + ((ARG3 \/ 8) * 512)) + ((ARG4 \/ 4) * 8)) + 6): f(RSP)","f(ARG1 , ARG2 , ARG3 , ARG4): ((([f(ARG1 , ARG2)] + (((((ARG3 \/ 8) * 8) + 1) * 64) + 192)) + ((ARG4 \/ 4) * 8)) + 6): f(RSP)","f(ARG1 , ARG2 , ARG3 , ARG4): ((([f(ARG1 , ARG2)] + (((((ARG3 \/ 8) * 8) + 1) * 64) + 256)) + ((ARG4 \/ 4) * 8)) + 6): f(RSP)","f(ARG1 , ARG2 , ARG3 , ARG4): (([f(ARG1 , ARG2)] + (((((ARG3 \/ 8) * 8) + 1) * 64) + 384)) + ((ARG4 \/ 4) * 8)): f(RSP)","f(ARG1 , ARG2 , ARG3 , ARG4): (([f(ARG1 , ARG2)] + (((((ARG3 \/ 8) * 8) + 1) * 64) + 128)) + ((ARG4 \/ 4) * 8)): f(RSP)","f(ARG1 , ARG2 , ARG3 , ARG4): ((([f(ARG1 , ARG2)] + ((((ARG3 \/ 8) * 8) + 1) * 64)) + ((ARG4 \/ 4) * 8)) + 2): f(RSP)","f(ARG1 , ARG2 , ARG3 , ARG4): ((([f(ARG1 , ARG2)] + (((((ARG3 \/ 8) * 8) + 1) * 64) + 320)) + ((ARG4 \/ 4) * 8)) + 2): f(RSP)","f(ARG1 , ARG2 , ARG3 , ARG4): ((([f(ARG1 , ARG2)] + (((((ARG3 \/ 8) * 8) + 1) * 64) + 64)) + ((ARG4 \/ 4) * 8)) + 4): f(RSP)","f(ARG1 , ARG2 , ARG3 , ARG4): ((([f(ARG1 , ARG2)] + (((((ARG3 \/ 8) * 8) + 1) * 64) + 256)) + ((ARG4 \/ 4) * 8)) + 2): f(RSP)","f(ARG1 , ARG2 , ARG3 , ARG4): (([f(ARG1 , ARG2)] + (((((ARG3 \/ 8) * 8) + 1) * 64) + 192)) + ((ARG4 \/ 4) * 8)): f(RSP)","f(ARG1 , ARG2 , ARG3 , ARG4): ((([f(ARG1 , ARG2)] + ((((ARG3 \/ 8) * 8) + 1) * 64)) + ((ARG4 \/ 4) * 8)) + 6): f(RSP)","f(ARG1 , ARG2 , ARG3 , ARG4): ((([f(ARG1 , ARG2)] + (((((ARG3 \/ 8) * 8) + 1) * 64) + 256)) + ((ARG4 \/ 4) * 8)) + 4): f(RSP)","f(ARG1 , ARG2 , ARG3 , ARG4): (([f(ARG1 , ARG2)] + (((((ARG3 \/ 8) * 8) + 1) * 64) + 64)) + ((ARG4 \/ 4) * 8)): f(RSP)"],"return":[]}